AdvanceForCaesar/__init__.py
AdvanceForCaesar/cepy.py
AdvanceForCaesar-2.0.3.dist-info/LICENSE
AdvanceForCaesar-2.0.3.dist-info/METADATA
AdvanceForCaesar-2.0.3.dist-info/WHEEL
AdvanceForCaesar-2.0.3.dist-info/top_level.txt
AdvanceForCaesar-2.0.3.dist-info/RECORD
