Metadata-Version: 2.1
Name: AdvanceForCaesar
Version: 2.0.3
Summary: An advanced Caesar cipher encryption tool that supports both encryption and decryption of text using a range of shift values.
Author: Guo Zilu,Gong Yifu,Zhang Zhichen
Author-email: sm37kx@126.com
License: MIT
Classifier: Programming Language :: Python :: 3
Classifier: License :: OSI Approved :: MIT License
Classifier: Operating System :: Microsoft :: Windows
License-File: LICENSE
